{
  "id" : "6a6b9eda-be1d-4215-9d34-087e80c276ac",
  "revisionNumber" : 1,
  "baseUrl" : "https://fhirsandbox-test.apigee.net/v2/MedicationDispense",
  "releaseVersion" : "1.0.0",
  "resources" : [ {
    "id" : "9debfd2a-d9db-482f-8412-3da9756a0ae1",
    "name" : "/{id}",
    "baseUrl" : "https://fhirsandbox-test.apigee.net/v2/MedicationDispense",
    "path" : "/{id}",
    "parameters" : [ {
      "dataType" : "string",
      "name" : "Content-Type",
      "options" : [ "application/json+fhir;charset=UTF-8", "application/xml+fhir;charset=UTF-8" ],
      "type" : "header"
    } ],
    "methods" : [ {
      "id" : "66264c9a-8b49-4b45-9999-27c835e6b854",
      "name" : "/{id}-get",
      "displayName" : "Read MedicationDispense ",
      "description" : "<p>Returns details of MedicationDispense having id given in path</p>\n",
      "verb" : "GET",
      "security" : [ "oauth-2-0" ],
      "parameters" : [ {
        "allowMultiple" : false,
        "dataType" : "string",
        "description" : "",
        "name" : "Content-Type",
        "options" : [ "application/json+fhir;charset=UTF-8", "application/xml+fhir;charset=UTF-8" ],
        "required" : false,
        "type" : "header"
      }, {
        "allowMultiple" : false,
        "dataType" : "string",
        "description" : "Format of data to be returned.",
        "name" : "_format",
        "required" : false,
        "type" : "query"
      }, {
        "allowMultiple" : false,
        "dataType" : "string",
        "description" : "The logical resource id associated with the MedicationDispense. Sample ids are: 3426, 3425, 3418, 3423, 5029.",
        "name" : "id",
        "required" : true,
        "type" : "template"
      }, {
        "allowMultiple" : false,
        "dataType" : "string",
        "description" : "Specify access token for API in the following format: Bearer [access_token].",
        "name" : "Authorization",
        "required" : false,
        "type" : "header"
      }, {
        "allowMultiple" : false,
        "dataType" : "string",
        "description" : "The Accept request-header field can be used to specify certain media types which are acceptable for the response.",
        "name" : "Accept",
        "required" : false,
        "type" : "header"
      } ],
      "body" : {
        "attachments" : [ ],
        "contentType" : "application/json+fhir;charset=UTF-8,application/xml+fhir;charset=UTF-8",
        "parameters" : [ ]
      },
      "response" : {
        "errors" : [ ],
        "parameters" : [ ]
      },
      "customAttributes" : {
        "SWAGGER_PRODUCES" : "[ \"application/json+fhir;charset=UTF-8\", \"application/xml+fhir;charset=UTF-8\" ]"
      },
      "createdTime" : 1443788735790,
      "modifiedTime" : 1443796137324,
      "apiRevisionId" : "6a6b9eda-be1d-4215-9d34-087e80c276ac",
      "baseUrl" : "https://fhirsandbox-test.apigee.net/v2/MedicationDispense",
      "methods" : [ ],
      "path" : "/{id}",
      "resourceId" : "9debfd2a-d9db-482f-8412-3da9756a0ae1",
      "resourceName" : "/{id}",
      "resources" : [ ],
      "revisionNumber" : 1
    } ],
    "customAttributes" : {
      "SWAGGER_RESOURCE_PATH" : "/{id}",
      "SWAGGER_PRODUCES" : "[ \"application/json+fhir;charset=UTF-8\", \"application/xml+fhir;charset=UTF-8\" ]",
      "SWAGGER_PROTOCOLS" : "[ \"https\" ]"
    },
    "createdTime" : 1443788735786,
    "apiRevisionId" : "6a6b9eda-be1d-4215-9d34-087e80c276ac",
    "resources" : [ ],
    "revisionNumber" : 1
  }, {
    "id" : "ee1689a0-084b-40e1-b63d-f520a7ecf498",
    "name" : "/$meta",
    "baseUrl" : "https://fhirsandbox-test.apigee.net/v2/MedicationDispense",
    "path" : "/$meta",
    "parameters" : [ {
      "dataType" : "string",
      "name" : "Content-Type",
      "options" : [ "application/json+fhir;charset=UTF-8", "application/xml+fhir;charset=UTF-8" ],
      "type" : "header"
    } ],
    "methods" : [ {
      "id" : "1d81d175-d878-4f09-92d8-db73364885f9",
      "name" : "/$meta-get",
      "displayName" : "MedicationDispenses Metadata",
      "description" : "<p>Retrieves a summary of the profiles, tags, and security labels for MedicationDispense.</p>\n",
      "verb" : "GET",
      "security" : [ "oauth-2-0" ],
      "parameters" : [ {
        "allowMultiple" : false,
        "dataType" : "string",
        "description" : "",
        "name" : "Content-Type",
        "options" : [ "application/json+fhir;charset=UTF-8", "application/xml+fhir;charset=UTF-8" ],
        "required" : false,
        "type" : "header"
      }, {
        "allowMultiple" : false,
        "dataType" : "string",
        "description" : "Format of data to be returned.",
        "name" : "_format",
        "required" : false,
        "type" : "query"
      }, {
        "allowMultiple" : false,
        "dataType" : "string",
        "description" : "Specify access token for API in the following format: Bearer [access_token].",
        "name" : "Authorization",
        "required" : false,
        "type" : "header"
      }, {
        "allowMultiple" : false,
        "dataType" : "string",
        "description" : "The Accept request-header field can be used to specify certain media types which are acceptable for the response.",
        "name" : "Accept",
        "required" : false,
        "type" : "header"
      } ],
      "body" : {
        "attachments" : [ ],
        "contentType" : "application/json+fhir;charset=UTF-8,application/xml+fhir;charset=UTF-8",
        "parameters" : [ ]
      },
      "response" : {
        "errors" : [ ],
        "parameters" : [ ]
      },
      "customAttributes" : {
        "SWAGGER_PRODUCES" : "[ \"application/json+fhir;charset=UTF-8\", \"application/xml+fhir;charset=UTF-8\" ]"
      },
      "createdTime" : 1443788735790,
      "modifiedTime" : 1443796138354,
      "apiRevisionId" : "6a6b9eda-be1d-4215-9d34-087e80c276ac",
      "baseUrl" : "https://fhirsandbox-test.apigee.net/v2/MedicationDispense",
      "methods" : [ ],
      "path" : "/$meta",
      "resourceId" : "ee1689a0-084b-40e1-b63d-f520a7ecf498",
      "resourceName" : "/$meta",
      "resources" : [ ],
      "revisionNumber" : 1
    } ],
    "customAttributes" : {
      "SWAGGER_RESOURCE_PATH" : "/$meta",
      "SWAGGER_PRODUCES" : "[ \"application/json+fhir;charset=UTF-8\", \"application/xml+fhir;charset=UTF-8\" ]",
      "SWAGGER_PROTOCOLS" : "[ \"https\" ]"
    },
    "createdTime" : 1443788735786,
    "apiRevisionId" : "6a6b9eda-be1d-4215-9d34-087e80c276ac",
    "resources" : [ ],
    "revisionNumber" : 1
  }, {
    "id" : "72f974bc-025c-4cd7-9d36-c0114cc31e70",
    "name" : "/{id}/_history/{vid}",
    "baseUrl" : "https://fhirsandbox-test.apigee.net/v2/MedicationDispense",
    "path" : "/{id}/_history/{vid}",
    "parameters" : [ {
      "dataType" : "string",
      "name" : "Content-Type",
      "options" : [ "application/json+fhir;charset=UTF-8", "application/xml+fhir;charset=UTF-8" ],
      "type" : "header"
    } ],
    "methods" : [ {
      "id" : "54165f17-29c2-4f23-b5ee-5c7437aa9007",
      "name" : "/{id}/_history/{vid}-get",
      "displayName" : "MedicationDispense Version Read",
      "description" : "<p>This interaction preforms a version specific read of MedicationDispense resource.</p>\n",
      "verb" : "GET",
      "security" : [ "oauth-2-0" ],
      "parameters" : [ {
        "allowMultiple" : false,
        "dataType" : "string",
        "description" : "",
        "name" : "Content-Type",
        "options" : [ "application/json+fhir;charset=UTF-8", "application/xml+fhir;charset=UTF-8" ],
        "required" : false,
        "type" : "header"
      }, {
        "allowMultiple" : false,
        "dataType" : "string",
        "description" : "Format of data to be returned.",
        "name" : "_format",
        "required" : false,
        "type" : "query"
      }, {
        "allowMultiple" : false,
        "dataType" : "string",
        "description" : "The logical resource id associated with the MedicationDispense. Sample ids are: 3426, 3425, 3418, 3423, 5029.",
        "name" : "id",
        "required" : true,
        "type" : "template"
      }, {
        "allowMultiple" : false,
        "dataType" : "string",
        "description" : "Version Id of MedicationDispense",
        "name" : "vid",
        "required" : true,
        "type" : "template"
      }, {
        "allowMultiple" : false,
        "dataType" : "string",
        "description" : "Specify access token for API in the following format: Bearer [access_token].",
        "name" : "Authorization",
        "required" : false,
        "type" : "header"
      }, {
        "allowMultiple" : false,
        "dataType" : "string",
        "description" : "The Accept request-header field can be used to specify certain media types which are acceptable for the response.",
        "name" : "Accept",
        "required" : false,
        "type" : "header"
      } ],
      "body" : {
        "attachments" : [ ],
        "contentType" : "application/json+fhir;charset=UTF-8,application/xml+fhir;charset=UTF-8",
        "parameters" : [ ]
      },
      "response" : {
        "errors" : [ ],
        "parameters" : [ ]
      },
      "customAttributes" : {
        "SWAGGER_PRODUCES" : "[ \"application/json+fhir;charset=UTF-8\", \"application/xml+fhir;charset=UTF-8\" ]"
      },
      "createdTime" : 1443788735791,
      "modifiedTime" : 1443796139293,
      "apiRevisionId" : "6a6b9eda-be1d-4215-9d34-087e80c276ac",
      "baseUrl" : "https://fhirsandbox-test.apigee.net/v2/MedicationDispense",
      "methods" : [ ],
      "path" : "/{id}/_history/{vid}",
      "resourceId" : "72f974bc-025c-4cd7-9d36-c0114cc31e70",
      "resourceName" : "/{id}/_history/{vid}",
      "resources" : [ ],
      "revisionNumber" : 1
    } ],
    "customAttributes" : {
      "SWAGGER_RESOURCE_PATH" : "/{id}/_history/{vid}",
      "SWAGGER_PRODUCES" : "[ \"application/json+fhir;charset=UTF-8\", \"application/xml+fhir;charset=UTF-8\" ]",
      "SWAGGER_PROTOCOLS" : "[ \"https\" ]"
    },
    "createdTime" : 1443788735786,
    "apiRevisionId" : "6a6b9eda-be1d-4215-9d34-087e80c276ac",
    "resources" : [ ],
    "revisionNumber" : 1
  }, {
    "id" : "99ae9f4b-74a1-46f6-b5d3-1d21f7dcef18",
    "name" : "/_history",
    "baseUrl" : "https://fhirsandbox-test.apigee.net/v2/MedicationDispense",
    "path" : "/_history",
    "parameters" : [ {
      "dataType" : "string",
      "name" : "Content-Type",
      "options" : [ "application/json+fhir;charset=UTF-8", "application/xml+fhir;charset=UTF-8" ],
      "type" : "header"
    } ],
    "methods" : [ {
      "id" : "db4ca240-dd0c-486a-9ea1-04e07c3a8995",
      "name" : "/_history-get",
      "displayName" : "MedicationDispenses History",
      "description" : "<p>It retrieves the history of all resources of MedicationDispense</p>\n",
      "verb" : "GET",
      "security" : [ "oauth-2-0" ],
      "parameters" : [ {
        "allowMultiple" : false,
        "dataType" : "string",
        "description" : "",
        "name" : "Content-Type",
        "options" : [ "application/json+fhir;charset=UTF-8", "application/xml+fhir;charset=UTF-8" ],
        "required" : false,
        "type" : "header"
      }, {
        "allowMultiple" : false,
        "dataType" : "string",
        "description" : "Format of data to be returned.",
        "name" : "_format",
        "required" : false,
        "type" : "query"
      }, {
        "allowMultiple" : false,
        "dataType" : "integer",
        "description" : "Number of records needed in response.",
        "name" : "_count",
        "required" : false,
        "type" : "query"
      }, {
        "allowMultiple" : false,
        "dataType" : "string",
        "description" : "Specify an instant to only include resource versions that were created at or after the given instant in time. An instant in time is known at least to the second and always includes a time zone.",
        "name" : "_since",
        "required" : false,
        "type" : "query"
      }, {
        "allowMultiple" : false,
        "dataType" : "string",
        "description" : "Specify access token for API in the following format: Bearer [access_token].",
        "name" : "Authorization",
        "required" : false,
        "type" : "header"
      }, {
        "allowMultiple" : false,
        "dataType" : "string",
        "description" : "The Accept request-header field can be used to specify certain media types which are acceptable for the response.",
        "name" : "Accept",
        "required" : false,
        "type" : "header"
      } ],
      "body" : {
        "attachments" : [ ],
        "contentType" : "application/json+fhir;charset=UTF-8,application/xml+fhir;charset=UTF-8",
        "parameters" : [ ]
      },
      "response" : {
        "errors" : [ ],
        "parameters" : [ ]
      },
      "customAttributes" : {
        "SWAGGER_PRODUCES" : "[ \"application/json+fhir;charset=UTF-8\", \"application/xml+fhir;charset=UTF-8\" ]"
      },
      "createdTime" : 1443788735790,
      "modifiedTime" : 1443796133015,
      "apiRevisionId" : "6a6b9eda-be1d-4215-9d34-087e80c276ac",
      "baseUrl" : "https://fhirsandbox-test.apigee.net/v2/MedicationDispense",
      "methods" : [ ],
      "path" : "/_history",
      "resourceId" : "99ae9f4b-74a1-46f6-b5d3-1d21f7dcef18",
      "resourceName" : "/_history",
      "resources" : [ ],
      "revisionNumber" : 1
    } ],
    "customAttributes" : {
      "SWAGGER_RESOURCE_PATH" : "/_history",
      "SWAGGER_PRODUCES" : "[ \"application/json+fhir;charset=UTF-8\", \"application/xml+fhir;charset=UTF-8\" ]",
      "SWAGGER_PROTOCOLS" : "[ \"https\" ]"
    },
    "createdTime" : 1443788735786,
    "apiRevisionId" : "6a6b9eda-be1d-4215-9d34-087e80c276ac",
    "resources" : [ ],
    "revisionNumber" : 1
  }, {
    "id" : "447c12f9-5e54-4c6b-8348-3ba96d039fe7",
    "name" : "/{id}/_history",
    "baseUrl" : "https://fhirsandbox-test.apigee.net/v2/MedicationDispense",
    "path" : "/{id}/_history",
    "parameters" : [ {
      "dataType" : "string",
      "name" : "Content-Type",
      "options" : [ "application/json+fhir;charset=UTF-8", "application/xml+fhir;charset=UTF-8" ],
      "type" : "header"
    } ],
    "methods" : [ {
      "id" : "f75f2c87-f2ee-4471-a518-0dadfd469b64",
      "name" : "/{id}/_history-get",
      "displayName" : "MedicationDispense History",
      "description" : "<p>It retrieves the history of a particular MedicationDispense identified by the given id in path.</p>\n",
      "verb" : "GET",
      "security" : [ "oauth-2-0" ],
      "parameters" : [ {
        "allowMultiple" : false,
        "dataType" : "string",
        "description" : "",
        "name" : "Content-Type",
        "options" : [ "application/json+fhir;charset=UTF-8", "application/xml+fhir;charset=UTF-8" ],
        "required" : false,
        "type" : "header"
      }, {
        "allowMultiple" : false,
        "dataType" : "string",
        "description" : "Format of data to be returned.",
        "name" : "_format",
        "required" : false,
        "type" : "query"
      }, {
        "allowMultiple" : false,
        "dataType" : "integer",
        "description" : "Number of records needed in response.",
        "name" : "_count",
        "required" : false,
        "type" : "query"
      }, {
        "allowMultiple" : false,
        "dataType" : "string",
        "description" : "Specify an instant to only include resource versions that were created at or after the given instant in time. An instant in time is known at least to the second and always includes a time zone.",
        "name" : "_since",
        "required" : false,
        "type" : "query"
      }, {
        "allowMultiple" : false,
        "dataType" : "string",
        "description" : "The logical resource id associated with the MedicationDispense. Sample ids are: 3426, 3425, 3418, 3423, 5029.",
        "name" : "id",
        "required" : true,
        "type" : "template"
      }, {
        "allowMultiple" : false,
        "dataType" : "string",
        "description" : "Specify access token for API in the following format: Bearer [access_token].",
        "name" : "Authorization",
        "required" : false,
        "type" : "header"
      }, {
        "allowMultiple" : false,
        "dataType" : "string",
        "description" : "The Accept request-header field can be used to specify certain media types which are acceptable for the response.",
        "name" : "Accept",
        "required" : false,
        "type" : "header"
      } ],
      "body" : {
        "attachments" : [ ],
        "contentType" : "application/json+fhir;charset=UTF-8,application/xml+fhir;charset=UTF-8",
        "parameters" : [ ]
      },
      "response" : {
        "errors" : [ ],
        "parameters" : [ ]
      },
      "customAttributes" : {
        "SWAGGER_PRODUCES" : "[ \"application/json+fhir;charset=UTF-8\", \"application/xml+fhir;charset=UTF-8\" ]"
      },
      "createdTime" : 1443788735790,
      "modifiedTime" : 1443796134172,
      "apiRevisionId" : "6a6b9eda-be1d-4215-9d34-087e80c276ac",
      "baseUrl" : "https://fhirsandbox-test.apigee.net/v2/MedicationDispense",
      "methods" : [ ],
      "path" : "/{id}/_history",
      "resourceId" : "447c12f9-5e54-4c6b-8348-3ba96d039fe7",
      "resourceName" : "/{id}/_history",
      "resources" : [ ],
      "revisionNumber" : 1
    } ],
    "customAttributes" : {
      "SWAGGER_RESOURCE_PATH" : "/{id}/_history",
      "SWAGGER_PRODUCES" : "[ \"application/json+fhir;charset=UTF-8\", \"application/xml+fhir;charset=UTF-8\" ]",
      "SWAGGER_PROTOCOLS" : "[ \"https\" ]"
    },
    "createdTime" : 1443788735786,
    "apiRevisionId" : "6a6b9eda-be1d-4215-9d34-087e80c276ac",
    "resources" : [ ],
    "revisionNumber" : 1
  }, {
    "id" : "96510dac-2d5c-4389-84af-356c1d3613bf",
    "name" : "/{id}/$meta",
    "baseUrl" : "https://fhirsandbox-test.apigee.net/v2/MedicationDispense",
    "path" : "/{id}/$meta",
    "parameters" : [ {
      "dataType" : "string",
      "name" : "Content-Type",
      "options" : [ "application/json+fhir;charset=UTF-8", "application/xml+fhir;charset=UTF-8" ],
      "type" : "header"
    } ],
    "methods" : [ {
      "id" : "8f26ee85-7ae5-4f9a-b4d7-3460e262c6ea",
      "name" : "/{id}/$meta-get",
      "displayName" : "MedicationDispense Metadata",
      "description" : "<p>Retrieves a summary of the profiles, tags, and security labels for given MedicationDispense.</p>\n",
      "verb" : "GET",
      "security" : [ "oauth-2-0" ],
      "parameters" : [ {
        "allowMultiple" : false,
        "dataType" : "string",
        "description" : "",
        "name" : "Content-Type",
        "options" : [ "application/json+fhir;charset=UTF-8", "application/xml+fhir;charset=UTF-8" ],
        "required" : false,
        "type" : "header"
      }, {
        "allowMultiple" : false,
        "dataType" : "string",
        "description" : "Format of data to be returned.",
        "name" : "_format",
        "required" : false,
        "type" : "query"
      }, {
        "allowMultiple" : false,
        "dataType" : "string",
        "description" : "The logical resource id associated with the MedicationDispense. Sample ids are: 3426, 3425, 3418, 3423, 5029.",
        "name" : "id",
        "required" : true,
        "type" : "template"
      }, {
        "allowMultiple" : false,
        "dataType" : "string",
        "description" : "Specify access token for API in the following format: Bearer [access_token].",
        "name" : "Authorization",
        "required" : false,
        "type" : "header"
      }, {
        "allowMultiple" : false,
        "dataType" : "string",
        "description" : "The Accept request-header field can be used to specify certain media types which are acceptable for the response.",
        "name" : "Accept",
        "required" : false,
        "type" : "header"
      } ],
      "body" : {
        "attachments" : [ ],
        "contentType" : "application/json+fhir;charset=UTF-8,application/xml+fhir;charset=UTF-8",
        "parameters" : [ ]
      },
      "response" : {
        "errors" : [ ],
        "parameters" : [ ]
      },
      "customAttributes" : {
        "SWAGGER_PRODUCES" : "[ \"application/json+fhir;charset=UTF-8\", \"application/xml+fhir;charset=UTF-8\" ]"
      },
      "createdTime" : 1443788735790,
      "modifiedTime" : 1443796135315,
      "apiRevisionId" : "6a6b9eda-be1d-4215-9d34-087e80c276ac",
      "baseUrl" : "https://fhirsandbox-test.apigee.net/v2/MedicationDispense",
      "methods" : [ ],
      "path" : "/{id}/$meta",
      "resourceId" : "96510dac-2d5c-4389-84af-356c1d3613bf",
      "resourceName" : "/{id}/$meta",
      "resources" : [ ],
      "revisionNumber" : 1
    } ],
    "customAttributes" : {
      "SWAGGER_RESOURCE_PATH" : "/{id}/$meta",
      "SWAGGER_PRODUCES" : "[ \"application/json+fhir;charset=UTF-8\", \"application/xml+fhir;charset=UTF-8\" ]",
      "SWAGGER_PROTOCOLS" : "[ \"https\" ]"
    },
    "createdTime" : 1443788735786,
    "apiRevisionId" : "6a6b9eda-be1d-4215-9d34-087e80c276ac",
    "resources" : [ ],
    "revisionNumber" : 1
  }, {
    "id" : "006616ec-70e2-445c-9375-1429b83daffd",
    "name" : "/_search",
    "baseUrl" : "https://fhirsandbox-test.apigee.net/v2/MedicationDispense",
    "path" : "/_search",
    "parameters" : [ {
      "dataType" : "string",
      "name" : "Content-Type",
      "options" : [ "application/json+fhir;charset=UTF-8", "application/xml+fhir;charset=UTF-8" ],
      "type" : "header"
    } ],
    "methods" : [ {
      "id" : "f1ed5d59-0925-40ba-9fbe-35f52b6907fd",
      "name" : "/_search-get",
      "displayName" : "MedicationDispenses Search",
      "description" : "<p>Search MedicationDispenses based on some filter criteria.</p>\n",
      "verb" : "GET",
      "security" : [ "oauth-2-0" ],
      "parameters" : [ {
        "allowMultiple" : false,
        "dataType" : "string",
        "description" : "",
        "name" : "Content-Type",
        "options" : [ "application/json+fhir;charset=UTF-8", "application/xml+fhir;charset=UTF-8" ],
        "required" : false,
        "type" : "header"
      }, {
        "allowMultiple" : false,
        "dataType" : "string",
        "description" : "Specify access token for API in the following format: Bearer [access_token].",
        "name" : "Authorization",
        "required" : false,
        "type" : "header"
      }, {
        "allowMultiple" : false,
        "dataType" : "string",
        "description" : "The Accept request-header field can be used to specify certain media types which are acceptable for the response.",
        "name" : "Accept",
        "required" : false,
        "type" : "header"
      }, {
        "allowMultiple" : false,
        "dataType" : "string",
        "description" : "Format of data to be returned.",
        "name" : "_format",
        "required" : false,
        "type" : "query"
      }, {
        "allowMultiple" : false,
        "dataType" : "string",
        "description" : "The logical resource id associated with the MedicationDispense. Sample ids are: 3426, 3425, 3418, 3423, 5029.",
        "name" : "_id",
        "required" : false,
        "type" : "query"
      }, {
        "allowMultiple" : false,
        "dataType" : "string",
        "description" : "Used to specify set of elements be returned as part of a resource. The _elements parameter consists of a comma separated list of base element names.",
        "name" : "_elements",
        "required" : false,
        "type" : "query"
      }, {
        "allowMultiple" : false,
        "dataType" : "string",
        "description" : "The search parameter _lastUpdated can be used to select resources based on the last time they were changed. The parameter format is yyyy-mm-ddThh:nn:ss(TZ). The prefixes >, >=, <= and < may be used on the parameter value.",
        "name" : "_lastUpdated",
        "required" : false,
        "type" : "query"
      }, {
        "allowMultiple" : false,
        "dataType" : "string",
        "description" : "The search parameter _lastUpdated can be used to select resources based on the last time they were changed. The parameter format is yyyy-mm-ddThh:nn:ss(TZ). The prefixes >, >=, <= and < may be used on the parameter value.",
        "name" : "_lastUpdated",
        "required" : false,
        "type" : "query"
      }, {
        "allowMultiple" : false,
        "dataType" : "string",
        "description" : "This parameter searches on the profile element in the meta element of the resource. Value can have following formats: [code] or [namespace]|[code] or |[code].",
        "name" : "_profile",
        "required" : false,
        "type" : "query"
      }, {
        "allowMultiple" : false,
        "dataType" : "string",
        "description" : "This parameter searches on the tags element in the meta element of the resource. Value can have following formats: [code] or [namespace]|[code] or |[code].",
        "name" : "_tag",
        "required" : false,
        "type" : "query"
      }, {
        "allowMultiple" : false,
        "dataType" : "string",
        "description" : "This parameter searches on the security element in the meta element of the resource. Value can have following formats: [code] or [namespace]|[code] or |[code].",
        "name" : "_security",
        "required" : false,
        "type" : "query"
      }, {
        "allowMultiple" : false,
        "dataType" : "integer",
        "description" : "The number of resources that should be returned in a single page.",
        "name" : "_count",
        "required" : false,
        "type" : "query"
      }, {
        "allowMultiple" : false,
        "dataType" : "boolean",
        "description" : "The _summary parameter requests the server to return only the elements marked as summary in their definition. ",
        "name" : "_summary",
        "required" : false,
        "type" : "query"
      }, {
        "allowMultiple" : false,
        "dataType" : "string",
        "description" : "This parameter can be used to fetch a particular resource, and any resources that it references. Parameter values for _include have 3 parts, separated by a : separator. 1. The name of the source resource from which the join comes. 2. The name of the search parameter which must be of type reference. 3.(Optional) A specific of type of target resource (for when the search parameter refers to multiple possible target types)",
        "name" : "_include",
        "required" : false,
        "type" : "query"
      }, {
        "allowMultiple" : false,
        "dataType" : "string",
        "description" : "This parameter can be used to fetch a particular resource, and any resources that refer to it. It can have a value of one of the possible search parameters. Parameter values for _revinclude have 3 parts, separated by a : separator. 1. The name of the source resource from which the join comes. 2. The name of the search parameter which must be of type reference. 3.(Optional) A specific of type of target resource (for when the search parameter refers to multiple possible target types)",
        "name" : "_revinclude",
        "required" : false,
        "type" : "query"
      }, {
        "allowMultiple" : false,
        "dataType" : "string",
        "description" : "Used to order the results in default(ascending) order. The value can be one of the possible search parameters. The _sort parameter can repeat to indicate sort order, with the repeats indicating a lower sort priority sequentially.",
        "name" : "_sort",
        "required" : false,
        "type" : "query"
      }, {
        "allowMultiple" : false,
        "dataType" : "string",
        "description" : "Used to order the results in ascending order. The value can be one of the possible search parameters. The _sort parameter can repeat to indicate sort order, with the repeats indicating a lower sort priority sequentially.",
        "name" : "_sort:asc",
        "required" : false,
        "type" : "query"
      }, {
        "allowMultiple" : false,
        "dataType" : "string",
        "description" : "Used to order the results in descending order. The value can be one of the possible search parameters. The _sort parameter can repeat to indicate sort order, with the repeats indicating a lower sort priority sequentially.",
        "name" : "_sort:desc",
        "required" : false,
        "type" : "query"
      }, {
        "allowMultiple" : false,
        "dataType" : "string",
        "description" : "Returns dispenses of this medicine code. Value can have following formats: [code] or [system]|[code] or |[code].",
        "name" : "code",
        "required" : false,
        "type" : "query"
      }, {
        "allowMultiple" : false,
        "dataType" : "string",
        "description" : "Return dispenses that should be sent to a specific destination (Location).",
        "name" : "destination",
        "required" : false,
        "type" : "query"
      }, {
        "allowMultiple" : false,
        "dataType" : "string",
        "description" : "Return all dispenses performed by a specific individual (Practitioner).",
        "name" : "dispenser",
        "required" : false,
        "type" : "query"
      }, {
        "allowMultiple" : false,
        "dataType" : "string",
        "description" : "Return dispenses with this external identity. Value can have following formats: [code] or [system]|[code] or |[code].",
        "name" : "identifier",
        "required" : false,
        "type" : "query"
      }, {
        "allowMultiple" : false,
        "dataType" : "string",
        "description" : "Returns dispenses of this medicine (Medication).",
        "name" : "medication",
        "required" : false,
        "type" : "query"
      }, {
        "allowMultiple" : false,
        "dataType" : "string",
        "description" : "The identity of a patient to list dispenses for (Patient).",
        "name" : "patient",
        "required" : false,
        "type" : "query"
      }, {
        "allowMultiple" : false,
        "dataType" : "string",
        "description" : "The identity of a prescription to list dispenses from (MedicationPrescription).",
        "name" : "prescription",
        "required" : false,
        "type" : "query"
      }, {
        "allowMultiple" : false,
        "dataType" : "string",
        "description" : "Who collected the medication (Patient, Practitioner).",
        "name" : "receiver",
        "required" : false,
        "type" : "query"
      }, {
        "allowMultiple" : false,
        "dataType" : "string",
        "description" : "Return all dispenses with the specified responsible party (Practitioner).",
        "name" : "responsibleparty",
        "required" : false,
        "type" : "query"
      }, {
        "allowMultiple" : false,
        "dataType" : "string",
        "description" : "Status of the dispense. Value can have following formats: [code] or [system]|[code] or |[code].",
        "name" : "status",
        "required" : false,
        "type" : "query"
      }, {
        "allowMultiple" : false,
        "dataType" : "string",
        "description" : "Return all dispenses of a specific type. Value can have following formats: [code] or [system]|[code] or |[code].",
        "name" : "type",
        "required" : false,
        "type" : "query"
      }, {
        "allowMultiple" : false,
        "dataType" : "string",
        "description" : "Date when medication handed over to patient (outpatient setting), or supplied to ward or clinic (inpatient setting). The date parameter format is yyyy-mm-ddThh:nn:ss(TZ). The prefixes >, >=, <= and < may be used on the parameter value.",
        "name" : "whenhandedover",
        "required" : false,
        "type" : "query"
      }, {
        "allowMultiple" : false,
        "dataType" : "string",
        "description" : "Date when medication handed over to patient (outpatient setting), or supplied to ward or clinic (inpatient setting). The date parameter format is yyyy-mm-ddThh:nn:ss(TZ). Two dates can be used to specify an interval. The prefixes >, >=, <= and < may be used on the parameter value.",
        "name" : "whenhandedover",
        "required" : false,
        "type" : "query"
      }, {
        "allowMultiple" : false,
        "dataType" : "string",
        "description" : "Date when medication prepared. The date parameter format is yyyy-mm-ddThh:nn:ss(TZ). The prefixes >, >=, <= and < may be used on the parameter value.",
        "name" : "whenprepared",
        "required" : false,
        "type" : "query"
      }, {
        "allowMultiple" : false,
        "dataType" : "string",
        "description" : "Date when medication prepared. The date parameter format is yyyy-mm-ddThh:nn:ss(TZ). Two dates can be used to specify an interval. The prefixes >, >=, <= and < may be used on the parameter value.",
        "name" : "whenprepared",
        "required" : false,
        "type" : "query"
      } ],
      "body" : {
        "attachments" : [ ],
        "contentType" : "application/json+fhir;charset=UTF-8,application/xml+fhir;charset=UTF-8",
        "parameters" : [ ]
      },
      "response" : {
        "errors" : [ ],
        "parameters" : [ ]
      },
      "customAttributes" : {
        "SWAGGER_PRODUCES" : "[ \"application/json+fhir;charset=UTF-8\", \"application/xml+fhir;charset=UTF-8\" ]"
      },
      "createdTime" : 1443788735790,
      "modifiedTime" : 1443796136484,
      "apiRevisionId" : "6a6b9eda-be1d-4215-9d34-087e80c276ac",
      "baseUrl" : "https://fhirsandbox-test.apigee.net/v2/MedicationDispense",
      "methods" : [ ],
      "path" : "/_search",
      "resourceId" : "006616ec-70e2-445c-9375-1429b83daffd",
      "resourceName" : "/_search",
      "resources" : [ ],
      "revisionNumber" : 1
    }, {
      "id" : "66756dc9-a9c7-4f65-9dbf-dd1b1cf1825b",
      "name" : "/_search-post",
      "displayName" : "MedicationDispenses Search",
      "description" : "<p>This interaction searches a set of MedicationDispenses based on some filter criteria. Search interactions take a series of parameters of name'='value pairs encoded as an application/x-www-form-urlencoded submission for a POST.</p>\n",
      "verb" : "POST",
      "security" : [ "oauth-2-0" ],
      "parameters" : [ {
        "allowMultiple" : false,
        "dataType" : "string",
        "description" : "",
        "name" : "Content-Type",
        "options" : [ "application/json+fhir;charset=UTF-8", "application/xml+fhir;charset=UTF-8" ],
        "required" : false,
        "type" : "header"
      }, {
        "allowMultiple" : false,
        "dataType" : "string",
        "description" : "Specify access token for API in the following format: Bearer [access_token].",
        "name" : "Authorization",
        "required" : false,
        "type" : "header"
      }, {
        "allowMultiple" : false,
        "dataType" : "string",
        "description" : "The Accept request-header field can be used to specify certain media types which are acceptable for the response.",
        "name" : "Accept",
        "required" : false,
        "type" : "header"
      }, {
        "allowMultiple" : false,
        "dataType" : "string",
        "description" : "Format of data to be returned.",
        "name" : "_format",
        "required" : false,
        "type" : "query"
      }, {
        "allowMultiple" : false,
        "dataType" : "string",
        "defaultValue" : "application/x-www-form-urlencoded",
        "description" : "Specifies the format of data in body",
        "name" : "Content-Type",
        "required" : true,
        "type" : "header"
      }, {
        "allowMultiple" : false,
        "dataType" : "string",
        "description" : "The logical resource id associated with the MedicationDispense. Sample ids are: 3426, 3425, 3418, 3423, 5029.",
        "name" : "_id",
        "required" : false,
        "type" : "query"
      }, {
        "allowMultiple" : false,
        "dataType" : "string",
        "description" : "Used to specify set of elements be returned as part of a resource. The _elements parameter consists of a comma separated list of base element names.",
        "name" : "_elements",
        "required" : false,
        "type" : "query"
      }, {
        "allowMultiple" : false,
        "dataType" : "string",
        "description" : "The search parameter _lastUpdated can be used to select resources based on the last time they were changed. The parameter format is yyyy-mm-ddThh:nn:ss(TZ). The prefixes >, >=, <= and < may be used on the parameter value.",
        "name" : "_lastUpdated",
        "required" : false,
        "type" : "query"
      }, {
        "allowMultiple" : false,
        "dataType" : "string",
        "description" : "The search parameter _lastUpdated can be used to select resources based on the last time they were changed. The parameter format is yyyy-mm-ddThh:nn:ss(TZ). The prefixes >, >=, <= and < may be used on the parameter value.",
        "name" : "_lastUpdated",
        "required" : false,
        "type" : "query"
      }, {
        "allowMultiple" : false,
        "dataType" : "string",
        "description" : "This parameter searches on the profile element in the meta element of the resource. Value can have following formats: [code] or [namespace]|[code] or |[code].",
        "name" : "_profile",
        "required" : false,
        "type" : "query"
      }, {
        "allowMultiple" : false,
        "dataType" : "string",
        "description" : "This parameter searches on the tags element in the meta element of the resource. Value can have following formats: [code] or [namespace]|[code] or |[code].",
        "name" : "_tag",
        "required" : false,
        "type" : "query"
      }, {
        "allowMultiple" : false,
        "dataType" : "string",
        "description" : "This parameter searches on the security element in the meta element of the resource. Value can have following formats: [code] or [namespace]|[code] or |[code].",
        "name" : "_security",
        "required" : false,
        "type" : "query"
      }, {
        "allowMultiple" : false,
        "dataType" : "integer",
        "description" : "The number of resources that should be returned in a single page.",
        "name" : "_count",
        "required" : false,
        "type" : "query"
      }, {
        "allowMultiple" : false,
        "dataType" : "boolean",
        "description" : "The _summary parameter requests the server to return only the elements marked as summary in their definition. ",
        "name" : "_summary",
        "required" : false,
        "type" : "query"
      }, {
        "allowMultiple" : false,
        "dataType" : "string",
        "description" : "This parameter can be used to fetch a particular resource, and any resources that it references. Parameter values for _include have 3 parts, separated by a : separator. 1. The name of the source resource from which the join comes. 2. The name of the search parameter which must be of type reference. 3.(Optional) A specific of type of target resource (for when the search parameter refers to multiple possible target types)",
        "name" : "_include",
        "required" : false,
        "type" : "query"
      }, {
        "allowMultiple" : false,
        "dataType" : "string",
        "description" : "This parameter can be used to fetch a particular resource, and any resources that refer to it. It can have a value of one of the possible search parameters. Parameter values for _revinclude have 3 parts, separated by a : separator. 1. The name of the source resource from which the join comes. 2. The name of the search parameter which must be of type reference. 3.(Optional) A specific of type of target resource (for when the search parameter refers to multiple possible target types)",
        "name" : "_revinclude",
        "required" : false,
        "type" : "query"
      }, {
        "allowMultiple" : false,
        "dataType" : "string",
        "description" : "Used to order the results in default(ascending) order. The value can be one of the possible search parameters. The _sort parameter can repeat to indicate sort order, with the repeats indicating a lower sort priority sequentially.",
        "name" : "_sort",
        "required" : false,
        "type" : "query"
      }, {
        "allowMultiple" : false,
        "dataType" : "string",
        "description" : "Used to order the results in ascending order. The value can be one of the possible search parameters. The _sort parameter can repeat to indicate sort order, with the repeats indicating a lower sort priority sequentially.",
        "name" : "_sort:asc",
        "required" : false,
        "type" : "query"
      }, {
        "allowMultiple" : false,
        "dataType" : "string",
        "description" : "Used to order the results in descending order. The value can be one of the possible search parameters. The _sort parameter can repeat to indicate sort order, with the repeats indicating a lower sort priority sequentially.",
        "name" : "_sort:desc",
        "required" : false,
        "type" : "query"
      }, {
        "allowMultiple" : false,
        "dataType" : "string",
        "description" : "Returns dispenses of this medicine code. Value can have following formats: [code] or [system]|[code] or |[code].",
        "name" : "code",
        "required" : false,
        "type" : "query"
      }, {
        "allowMultiple" : false,
        "dataType" : "string",
        "description" : "Return dispenses that should be sent to a specific destination (Location).",
        "name" : "destination",
        "required" : false,
        "type" : "query"
      }, {
        "allowMultiple" : false,
        "dataType" : "string",
        "description" : "Return all dispenses performed by a specific individual (Practitioner).",
        "name" : "dispenser",
        "required" : false,
        "type" : "query"
      }, {
        "allowMultiple" : false,
        "dataType" : "string",
        "description" : "Return dispenses with this external identity. Value can have following formats: [code] or [system]|[code] or |[code].",
        "name" : "identifier",
        "required" : false,
        "type" : "query"
      }, {
        "allowMultiple" : false,
        "dataType" : "string",
        "description" : "Returns dispenses of this medicine (Medication).",
        "name" : "medication",
        "required" : false,
        "type" : "query"
      }, {
        "allowMultiple" : false,
        "dataType" : "string",
        "description" : "The identity of a patient to list dispenses for (Patient).",
        "name" : "patient",
        "required" : false,
        "type" : "query"
      }, {
        "allowMultiple" : false,
        "dataType" : "string",
        "description" : "The identity of a prescription to list dispenses from (MedicationPrescription).",
        "name" : "prescription",
        "required" : false,
        "type" : "query"
      }, {
        "allowMultiple" : false,
        "dataType" : "string",
        "description" : "Who collected the medication (Patient, Practitioner).",
        "name" : "receiver",
        "required" : false,
        "type" : "query"
      }, {
        "allowMultiple" : false,
        "dataType" : "string",
        "description" : "Return all dispenses with the specified responsible party (Practitioner).",
        "name" : "responsibleparty",
        "required" : false,
        "type" : "query"
      }, {
        "allowMultiple" : false,
        "dataType" : "string",
        "description" : "Status of the dispense. Value can have following formats: [code] or [system]|[code] or |[code].",
        "name" : "status",
        "required" : false,
        "type" : "query"
      }, {
        "allowMultiple" : false,
        "dataType" : "string",
        "description" : "Return all dispenses of a specific type. Value can have following formats: [code] or [system]|[code] or |[code].",
        "name" : "type",
        "required" : false,
        "type" : "query"
      }, {
        "allowMultiple" : false,
        "dataType" : "string",
        "description" : "Date when medication handed over to patient (outpatient setting), or supplied to ward or clinic (inpatient setting). The date parameter format is yyyy-mm-ddThh:nn:ss(TZ). The prefixes >, >=, <= and < may be used on the parameter value.",
        "name" : "whenhandedover",
        "required" : false,
        "type" : "query"
      }, {
        "allowMultiple" : false,
        "dataType" : "string",
        "description" : "Date when medication handed over to patient (outpatient setting), or supplied to ward or clinic (inpatient setting). The date parameter format is yyyy-mm-ddThh:nn:ss(TZ). Two dates can be used to specify an interval. The prefixes >, >=, <= and < may be used on the parameter value.",
        "name" : "whenhandedover",
        "required" : false,
        "type" : "query"
      }, {
        "allowMultiple" : false,
        "dataType" : "string",
        "description" : "Date when medication prepared. The date parameter format is yyyy-mm-ddThh:nn:ss(TZ). The prefixes >, >=, <= and < may be used on the parameter value.",
        "name" : "whenprepared",
        "required" : false,
        "type" : "query"
      }, {
        "allowMultiple" : false,
        "dataType" : "string",
        "description" : "Date when medication prepared. The date parameter format is yyyy-mm-ddThh:nn:ss(TZ). Two dates can be used to specify an interval. The prefixes >, >=, <= and < may be used on the parameter value.",
        "name" : "whenprepared",
        "required" : false,
        "type" : "query"
      } ],
      "body" : {
        "attachments" : [ ],
        "contentType" : "application/json+fhir;charset=UTF-8,application/xml+fhir;charset=UTF-8",
        "parameters" : [ {
          "allowMultiple" : false,
          "dataType" : "string",
          "description" : "The logical resource id associated with the MedicationDispense. Sample ids are: 3426, 3425, 3418, 3423, 5029.",
          "name" : "_id",
          "required" : false,
          "type" : "body"
        }, {
          "allowMultiple" : false,
          "dataType" : "string",
          "description" : "Used to specify set of elements be returned as part of a resource. The _elements parameter consists of a comma separated list of base element names.",
          "name" : "_elements",
          "required" : false,
          "type" : "body"
        }, {
          "allowMultiple" : false,
          "dataType" : "string",
          "description" : "The search parameter _lastUpdated can be used to select resources based on the last time they were changed. The parameter format is yyyy-mm-ddThh:nn:ss(TZ). The prefixes >, >=, <= and < may be used on the parameter value.",
          "name" : "_lastUpdated",
          "required" : false,
          "type" : "body"
        }, {
          "allowMultiple" : false,
          "dataType" : "string",
          "description" : "The search parameter _lastUpdated can be used to select resources based on the last time they were changed. The parameter format is yyyy-mm-ddThh:nn:ss(TZ). The prefixes >, >=, <= and < may be used on the parameter value.",
          "name" : "_lastUpdated",
          "required" : false,
          "type" : "body"
        }, {
          "allowMultiple" : false,
          "dataType" : "string",
          "description" : "This parameter searches on the profile element in the meta element of the resource. Value can have following formats: [code] or [namespace]|[code] or |[code].",
          "name" : "_profile",
          "required" : false,
          "type" : "body"
        }, {
          "allowMultiple" : false,
          "dataType" : "string",
          "description" : "This parameter searches on the tags element in the meta element of the resource. Value can have following formats: [code] or [namespace]|[code] or |[code].",
          "name" : "_tag",
          "required" : false,
          "type" : "body"
        }, {
          "allowMultiple" : false,
          "dataType" : "string",
          "description" : "This parameter searches on the security element in the meta element of the resource. Value can have following formats: [code] or [namespace]|[code] or |[code].",
          "name" : "_security",
          "required" : false,
          "type" : "body"
        }, {
          "allowMultiple" : false,
          "dataType" : "integer",
          "description" : "The number of resources that should be returned in a single page.",
          "name" : "_count",
          "required" : false,
          "type" : "body"
        }, {
          "allowMultiple" : false,
          "dataType" : "boolean",
          "description" : "The _summary parameter requests the server to return only the elements marked as summary in their definition. ",
          "name" : "_summary",
          "required" : false,
          "type" : "body"
        }, {
          "allowMultiple" : false,
          "dataType" : "string",
          "description" : "This parameter can be used to fetch a particular resource, and any resources that it references. Parameter values for _include have 3 parts, separated by a : separator. 1. The name of the source resource from which the join comes. 2. The name of the search parameter which must be of type reference. 3.(Optional) A specific of type of target resource (for when the search parameter refers to multiple possible target types)",
          "name" : "_include",
          "required" : false,
          "type" : "body"
        }, {
          "allowMultiple" : false,
          "dataType" : "string",
          "description" : "This parameter can be used to fetch a particular resource, and any resources that refer to it. It can have a value of one of the possible search parameters. Parameter values for _revinclude have 3 parts, separated by a : separator. 1. The name of the source resource from which the join comes. 2. The name of the search parameter which must be of type reference. 3.(Optional) A specific of type of target resource (for when the search parameter refers to multiple possible target types)",
          "name" : "_revinclude",
          "required" : false,
          "type" : "body"
        }, {
          "allowMultiple" : false,
          "dataType" : "string",
          "description" : "Used to order the results in default(ascending) order. The value can be one of the possible search parameters. The _sort parameter can repeat to indicate sort order, with the repeats indicating a lower sort priority sequentially.",
          "name" : "_sort",
          "required" : false,
          "type" : "body"
        }, {
          "allowMultiple" : false,
          "dataType" : "string",
          "description" : "Used to order the results in ascending order. The value can be one of the possible search parameters. The _sort parameter can repeat to indicate sort order, with the repeats indicating a lower sort priority sequentially.",
          "name" : "_sort:asc",
          "required" : false,
          "type" : "body"
        }, {
          "allowMultiple" : false,
          "dataType" : "string",
          "description" : "Used to order the results in descending order. The value can be one of the possible search parameters. The _sort parameter can repeat to indicate sort order, with the repeats indicating a lower sort priority sequentially.",
          "name" : "_sort:desc",
          "required" : false,
          "type" : "body"
        }, {
          "allowMultiple" : false,
          "dataType" : "string",
          "description" : "Returns dispenses of this medicine code. Value can have following formats: [code] or [system]|[code] or |[code].",
          "name" : "code",
          "required" : false,
          "type" : "body"
        }, {
          "allowMultiple" : false,
          "dataType" : "string",
          "description" : "Return dispenses that should be sent to a specific destination (Location).",
          "name" : "destination",
          "required" : false,
          "type" : "body"
        }, {
          "allowMultiple" : false,
          "dataType" : "string",
          "description" : "Return all dispenses performed by a specific individual (Practitioner).",
          "name" : "dispenser",
          "required" : false,
          "type" : "body"
        }, {
          "allowMultiple" : false,
          "dataType" : "string",
          "description" : "Return dispenses with this external identity. Value can have following formats: [code] or [system]|[code] or |[code].",
          "name" : "identifier",
          "required" : false,
          "type" : "body"
        }, {
          "allowMultiple" : false,
          "dataType" : "string",
          "description" : "Returns dispenses of this medicine (Medication).",
          "name" : "medication",
          "required" : false,
          "type" : "body"
        }, {
          "allowMultiple" : false,
          "dataType" : "string",
          "description" : "The identity of a patient to list dispenses for (Patient).",
          "name" : "patient",
          "required" : false,
          "type" : "body"
        }, {
          "allowMultiple" : false,
          "dataType" : "string",
          "description" : "The identity of a prescription to list dispenses from (MedicationPrescription).",
          "name" : "prescription",
          "required" : false,
          "type" : "body"
        }, {
          "allowMultiple" : false,
          "dataType" : "string",
          "description" : "Who collected the medication (Patient, Practitioner).",
          "name" : "receiver",
          "required" : false,
          "type" : "body"
        }, {
          "allowMultiple" : false,
          "dataType" : "string",
          "description" : "Return all dispenses with the specified responsible party (Practitioner).",
          "name" : "responsibleparty",
          "required" : false,
          "type" : "body"
        }, {
          "allowMultiple" : false,
          "dataType" : "string",
          "description" : "Status of the dispense. Value can have following formats: [code] or [system]|[code] or |[code].",
          "name" : "status",
          "required" : false,
          "type" : "body"
        }, {
          "allowMultiple" : false,
          "dataType" : "string",
          "description" : "Return all dispenses of a specific type. Value can have following formats: [code] or [system]|[code] or |[code].",
          "name" : "type",
          "required" : false,
          "type" : "body"
        }, {
          "allowMultiple" : false,
          "dataType" : "string",
          "description" : "Date when medication handed over to patient (outpatient setting), or supplied to ward or clinic (inpatient setting). The date parameter format is yyyy-mm-ddThh:nn:ss(TZ). The prefixes >, >=, <= and < may be used on the parameter value.",
          "name" : "whenhandedover",
          "required" : false,
          "type" : "body"
        }, {
          "allowMultiple" : false,
          "dataType" : "string",
          "description" : "Date when medication handed over to patient (outpatient setting), or supplied to ward or clinic (inpatient setting). The date parameter format is yyyy-mm-ddThh:nn:ss(TZ). Two dates can be used to specify an interval. The prefixes >, >=, <= and < may be used on the parameter value.",
          "name" : "whenhandedover",
          "required" : false,
          "type" : "body"
        }, {
          "allowMultiple" : false,
          "dataType" : "string",
          "description" : "Date when medication prepared. The date parameter format is yyyy-mm-ddThh:nn:ss(TZ). The prefixes >, >=, <= and < may be used on the parameter value.",
          "name" : "whenprepared",
          "required" : false,
          "type" : "body"
        }, {
          "allowMultiple" : false,
          "dataType" : "string",
          "description" : "Date when medication prepared. The date parameter format is yyyy-mm-ddThh:nn:ss(TZ). Two dates can be used to specify an interval. The prefixes >, >=, <= and < may be used on the parameter value.",
          "name" : "whenprepared",
          "required" : false,
          "type" : "body"
        } ]
      },
      "response" : {
        "errors" : [ ],
        "parameters" : [ ]
      },
      "customAttributes" : {
        "SWAGGER_PRODUCES" : "[ \"application/json+fhir;charset=UTF-8\", \"application/xml+fhir;charset=UTF-8\" ]"
      },
      "createdTime" : 1443788735790,
      "modifiedTime" : 1443796130301,
      "apiRevisionId" : "6a6b9eda-be1d-4215-9d34-087e80c276ac",
      "baseUrl" : "https://fhirsandbox-test.apigee.net/v2/MedicationDispense",
      "methods" : [ ],
      "path" : "/_search",
      "resourceId" : "006616ec-70e2-445c-9375-1429b83daffd",
      "resourceName" : "/_search",
      "resources" : [ ],
      "revisionNumber" : 1
    } ],
    "customAttributes" : {
      "SWAGGER_RESOURCE_PATH" : "/_search",
      "SWAGGER_PRODUCES" : "[ \"application/json+fhir;charset=UTF-8\", \"application/xml+fhir;charset=UTF-8\" ]",
      "SWAGGER_PROTOCOLS" : "[ \"https\" ]"
    },
    "createdTime" : 1443788735786,
    "apiRevisionId" : "6a6b9eda-be1d-4215-9d34-087e80c276ac",
    "resources" : [ ],
    "revisionNumber" : 1
  }, {
    "id" : "c5beda39-871d-42b1-baad-dc5a29058ae4",
    "name" : "",
    "baseUrl" : "https://fhirsandbox-test.apigee.net/v2/MedicationDispense",
    "path" : "",
    "parameters" : [ {
      "dataType" : "string",
      "name" : "Content-Type",
      "options" : [ "application/json+fhir;charset=UTF-8", "application/xml+fhir;charset=UTF-8" ],
      "type" : "header"
    } ],
    "methods" : [ {
      "id" : "e64d316b-863c-499b-b118-defa28ea468d",
      "name" : "-get",
      "displayName" : "Read MedicationDispenses",
      "description" : "<p>Returns MedicationDispenses based on filter criteria OR Provides provision for pagination (stateid, page, page_size &amp; _pretty are query parameters used for Paging).</p>\n",
      "verb" : "GET",
      "security" : [ "oauth-2-0" ],
      "parameters" : [ {
        "allowMultiple" : false,
        "dataType" : "string",
        "description" : "",
        "name" : "Content-Type",
        "options" : [ "application/json+fhir;charset=UTF-8", "application/xml+fhir;charset=UTF-8" ],
        "required" : false,
        "type" : "header"
      }, {
        "allowMultiple" : false,
        "dataType" : "string",
        "description" : "Specify access token for API in the following format: Bearer [access_token].",
        "name" : "Authorization",
        "required" : false,
        "type" : "header"
      }, {
        "allowMultiple" : false,
        "dataType" : "string",
        "description" : "The Accept request-header field can be used to specify certain media types which are acceptable for the response.",
        "name" : "Accept",
        "required" : false,
        "type" : "header"
      }, {
        "allowMultiple" : false,
        "dataType" : "string",
        "description" : "Format of data to be returned.",
        "name" : "_format",
        "required" : false,
        "type" : "query"
      }, {
        "allowMultiple" : false,
        "dataType" : "string",
        "description" : "The logical resource id associated with the MedicationDispense. Sample ids are: 3426, 3425, 3418, 3423, 5029.",
        "name" : "_id",
        "required" : false,
        "type" : "query"
      }, {
        "allowMultiple" : false,
        "dataType" : "string",
        "description" : "Used to specify set of elements be returned as part of a resource. The _elements parameter consists of a comma separated list of base element names.",
        "name" : "_elements",
        "required" : false,
        "type" : "query"
      }, {
        "allowMultiple" : false,
        "dataType" : "string",
        "description" : "The search parameter _lastUpdated can be used to select resources based on the last time they were changed. The parameter format is yyyy-mm-ddThh:nn:ss(TZ). The prefixes >, >=, <= and < may be used on the parameter value.",
        "name" : "_lastUpdated",
        "required" : false,
        "type" : "query"
      }, {
        "allowMultiple" : false,
        "dataType" : "string",
        "description" : "The search parameter _lastUpdated can be used to select resources based on the last time they were changed. The parameter format is yyyy-mm-ddThh:nn:ss(TZ). The prefixes >, >=, <= and < may be used on the parameter value.",
        "name" : "_lastUpdated",
        "required" : false,
        "type" : "query"
      }, {
        "allowMultiple" : false,
        "dataType" : "string",
        "description" : "This parameter searches on the profile element in the meta element of the resource. Value can have following formats: [code] or [namespace]|[code] or |[code].",
        "name" : "_profile",
        "required" : false,
        "type" : "query"
      }, {
        "allowMultiple" : false,
        "dataType" : "string",
        "description" : "This parameter searches on the tags element in the meta element of the resource. Value can have following formats: [code] or [namespace]|[code] or |[code].",
        "name" : "_tag",
        "required" : false,
        "type" : "query"
      }, {
        "allowMultiple" : false,
        "dataType" : "string",
        "description" : "This parameter searches on the security element in the meta element of the resource. Value can have following formats: [code] or [namespace]|[code] or |[code].",
        "name" : "_security",
        "required" : false,
        "type" : "query"
      }, {
        "allowMultiple" : false,
        "dataType" : "integer",
        "description" : "The number of resources that should be returned in a single page.",
        "name" : "_count",
        "required" : false,
        "type" : "query"
      }, {
        "allowMultiple" : false,
        "dataType" : "boolean",
        "description" : "The _summary parameter requests the server to return only the elements marked as summary in their definition. ",
        "name" : "_summary",
        "required" : false,
        "type" : "query"
      }, {
        "allowMultiple" : false,
        "dataType" : "string",
        "description" : "This parameter can be used to fetch a particular resource, and any resources that it references. Parameter values for _include have 3 parts, separated by a : separator. 1. The name of the source resource from which the join comes. 2. The name of the search parameter which must be of type reference. 3.(Optional) A specific of type of target resource (for when the search parameter refers to multiple possible target types)",
        "name" : "_include",
        "required" : false,
        "type" : "query"
      }, {
        "allowMultiple" : false,
        "dataType" : "string",
        "description" : "This parameter can be used to fetch a particular resource, and any resources that refer to it. It can have a value of one of the possible search parameters. Parameter values for _revinclude have 3 parts, separated by a : separator. 1. The name of the source resource from which the join comes. 2. The name of the search parameter which must be of type reference. 3.(Optional) A specific of type of target resource (for when the search parameter refers to multiple possible target types)",
        "name" : "_revinclude",
        "required" : false,
        "type" : "query"
      }, {
        "allowMultiple" : false,
        "dataType" : "string",
        "description" : "Used to order the results in default(ascending) order. The value can be one of the possible search parameters. The _sort parameter can repeat to indicate sort order, with the repeats indicating a lower sort priority sequentially.",
        "name" : "_sort",
        "required" : false,
        "type" : "query"
      }, {
        "allowMultiple" : false,
        "dataType" : "string",
        "description" : "Used to order the results in ascending order. The value can be one of the possible search parameters. The _sort parameter can repeat to indicate sort order, with the repeats indicating a lower sort priority sequentially.",
        "name" : "_sort:asc",
        "required" : false,
        "type" : "query"
      }, {
        "allowMultiple" : false,
        "dataType" : "string",
        "description" : "Used to order the results in descending order. The value can be one of the possible search parameters. The _sort parameter can repeat to indicate sort order, with the repeats indicating a lower sort priority sequentially.",
        "name" : "_sort:desc",
        "required" : false,
        "type" : "query"
      }, {
        "allowMultiple" : false,
        "dataType" : "string",
        "description" : "Returns dispenses of this medicine code. Value can have following formats: [code] or [system]|[code] or |[code].",
        "name" : "code",
        "required" : false,
        "type" : "query"
      }, {
        "allowMultiple" : false,
        "dataType" : "string",
        "description" : "Return dispenses that should be sent to a specific destination (Location).",
        "name" : "destination",
        "required" : false,
        "type" : "query"
      }, {
        "allowMultiple" : false,
        "dataType" : "string",
        "description" : "Return all dispenses performed by a specific individual (Practitioner).",
        "name" : "dispenser",
        "required" : false,
        "type" : "query"
      }, {
        "allowMultiple" : false,
        "dataType" : "string",
        "description" : "Return dispenses with this external identity. Value can have following formats: [code] or [system]|[code] or |[code].",
        "name" : "identifier",
        "required" : false,
        "type" : "query"
      }, {
        "allowMultiple" : false,
        "dataType" : "string",
        "description" : "Returns dispenses of this medicine (Medication).",
        "name" : "medication",
        "required" : false,
        "type" : "query"
      }, {
        "allowMultiple" : false,
        "dataType" : "string",
        "description" : "The identity of a patient to list dispenses for (Patient).",
        "name" : "patient",
        "required" : false,
        "type" : "query"
      }, {
        "allowMultiple" : false,
        "dataType" : "string",
        "description" : "The identity of a prescription to list dispenses from (MedicationPrescription).",
        "name" : "prescription",
        "required" : false,
        "type" : "query"
      }, {
        "allowMultiple" : false,
        "dataType" : "string",
        "description" : "Who collected the medication (Patient, Practitioner).",
        "name" : "receiver",
        "required" : false,
        "type" : "query"
      }, {
        "allowMultiple" : false,
        "dataType" : "string",
        "description" : "Return all dispenses with the specified responsible party (Practitioner).",
        "name" : "responsibleparty",
        "required" : false,
        "type" : "query"
      }, {
        "allowMultiple" : false,
        "dataType" : "string",
        "description" : "Status of the dispense. Value can have following formats: [code] or [system]|[code] or |[code].",
        "name" : "status",
        "required" : false,
        "type" : "query"
      }, {
        "allowMultiple" : false,
        "dataType" : "string",
        "description" : "Return all dispenses of a specific type. Value can have following formats: [code] or [system]|[code] or |[code].",
        "name" : "type",
        "required" : false,
        "type" : "query"
      }, {
        "allowMultiple" : false,
        "dataType" : "string",
        "description" : "Date when medication handed over to patient (outpatient setting), or supplied to ward or clinic (inpatient setting). The date parameter format is yyyy-mm-ddThh:nn:ss(TZ). The prefixes >, >=, <= and < may be used on the parameter value.",
        "name" : "whenhandedover",
        "required" : false,
        "type" : "query"
      }, {
        "allowMultiple" : false,
        "dataType" : "string",
        "description" : "Date when medication handed over to patient (outpatient setting), or supplied to ward or clinic (inpatient setting). The date parameter format is yyyy-mm-ddThh:nn:ss(TZ). Two dates can be used to specify an interval. The prefixes >, >=, <= and < may be used on the parameter value.",
        "name" : "whenhandedover",
        "required" : false,
        "type" : "query"
      }, {
        "allowMultiple" : false,
        "dataType" : "string",
        "description" : "Date when medication prepared. The date parameter format is yyyy-mm-ddThh:nn:ss(TZ). The prefixes >, >=, <= and < may be used on the parameter value.",
        "name" : "whenprepared",
        "required" : false,
        "type" : "query"
      }, {
        "allowMultiple" : false,
        "dataType" : "string",
        "description" : "Date when medication prepared. The date parameter format is yyyy-mm-ddThh:nn:ss(TZ). Two dates can be used to specify an interval. The prefixes >, >=, <= and < may be used on the parameter value.",
        "name" : "whenprepared",
        "required" : false,
        "type" : "query"
      }, {
        "allowMultiple" : false,
        "dataType" : "string",
        "description" : "Unique id associated with a page.",
        "name" : "stateid",
        "required" : false,
        "type" : "query"
      }, {
        "allowMultiple" : false,
        "dataType" : "number",
        "description" : "MedicationDispense resource offset.",
        "name" : "page",
        "required" : false,
        "type" : "query"
      }, {
        "allowMultiple" : false,
        "dataType" : "number",
        "description" : "The number of MedicationDispense resources requested in a page.",
        "name" : "page_size",
        "required" : false,
        "type" : "query"
      }, {
        "allowMultiple" : false,
        "dataType" : "boolean",
        "description" : "Set true to get prettified data.",
        "name" : "_pretty",
        "required" : false,
        "type" : "query"
      } ],
      "body" : {
        "attachments" : [ ],
        "contentType" : "application/json+fhir;charset=UTF-8,application/xml+fhir;charset=UTF-8",
        "parameters" : [ ]
      },
      "response" : {
        "errors" : [ ],
        "parameters" : [ ]
      },
      "customAttributes" : {
        "SWAGGER_PRODUCES" : "[ \"application/json+fhir;charset=UTF-8\", \"application/xml+fhir;charset=UTF-8\" ]"
      },
      "createdTime" : 1443788735790,
      "modifiedTime" : 1443796131019,
      "apiRevisionId" : "6a6b9eda-be1d-4215-9d34-087e80c276ac",
      "baseUrl" : "https://fhirsandbox-test.apigee.net/v2/MedicationDispense",
      "methods" : [ ],
      "path" : "",
      "resourceId" : "c5beda39-871d-42b1-baad-dc5a29058ae4",
      "resourceName" : "",
      "resources" : [ ],
      "revisionNumber" : 1
    } ],
    "customAttributes" : {
      "SWAGGER_RESOURCE_PATH" : "",
      "SWAGGER_PRODUCES" : "[ \"application/json+fhir;charset=UTF-8\", \"application/xml+fhir;charset=UTF-8\" ]",
      "SWAGGER_PROTOCOLS" : "[ \"https\" ]"
    },
    "createdTime" : 1443788735786,
    "apiRevisionId" : "6a6b9eda-be1d-4215-9d34-087e80c276ac",
    "resources" : [ ],
    "revisionNumber" : 1
  }, {
    "id" : "6b686c69-b331-491b-98f1-a63e99d1755e",
    "name" : "/{id}/_history/{vid}/$meta",
    "baseUrl" : "https://fhirsandbox-test.apigee.net/v2/MedicationDispense",
    "path" : "/{id}/_history/{vid}/$meta",
    "parameters" : [ {
      "dataType" : "string",
      "name" : "Content-Type",
      "options" : [ "application/json+fhir;charset=UTF-8", "application/xml+fhir;charset=UTF-8" ],
      "type" : "header"
    } ],
    "methods" : [ {
      "id" : "04f47683-f053-4dd7-973f-6b38068d98f5",
      "name" : "/{id}/_history/{vid}/$meta-get",
      "displayName" : "MedicationDispense Version based Metadata",
      "description" : "<p>Retrieves a summary of the profiles, tags, and security labels for given version of the MedicationDispense.</p>\n",
      "verb" : "GET",
      "security" : [ "oauth-2-0" ],
      "parameters" : [ {
        "allowMultiple" : false,
        "dataType" : "string",
        "description" : "",
        "name" : "Content-Type",
        "options" : [ "application/json+fhir;charset=UTF-8", "application/xml+fhir;charset=UTF-8" ],
        "required" : false,
        "type" : "header"
      }, {
        "allowMultiple" : false,
        "dataType" : "string",
        "description" : "Format of data to be returned.",
        "name" : "_format",
        "required" : false,
        "type" : "query"
      }, {
        "allowMultiple" : false,
        "dataType" : "string",
        "description" : "The logical resource id associated with the MedicationDispense. Sample ids are: 3426, 3425, 3418, 3423, 5029.",
        "name" : "id",
        "required" : true,
        "type" : "template"
      }, {
        "allowMultiple" : false,
        "dataType" : "string",
        "description" : "Version Id of MedicationDispense.",
        "name" : "vid",
        "required" : true,
        "type" : "template"
      }, {
        "allowMultiple" : false,
        "dataType" : "string",
        "description" : "Specify access token for API in the following format: Bearer [access_token].",
        "name" : "Authorization",
        "required" : false,
        "type" : "header"
      }, {
        "allowMultiple" : false,
        "dataType" : "string",
        "description" : "The Accept request-header field can be used to specify certain media types which are acceptable for the response.",
        "name" : "Accept",
        "required" : false,
        "type" : "header"
      } ],
      "body" : {
        "attachments" : [ ],
        "contentType" : "application/json+fhir;charset=UTF-8,application/xml+fhir;charset=UTF-8",
        "parameters" : [ ]
      },
      "response" : {
        "errors" : [ ],
        "parameters" : [ ]
      },
      "customAttributes" : {
        "SWAGGER_PRODUCES" : "[ \"application/json+fhir;charset=UTF-8\", \"application/xml+fhir;charset=UTF-8\" ]"
      },
      "createdTime" : 1443788735791,
      "modifiedTime" : 1443796131227,
      "apiRevisionId" : "6a6b9eda-be1d-4215-9d34-087e80c276ac",
      "baseUrl" : "https://fhirsandbox-test.apigee.net/v2/MedicationDispense",
      "methods" : [ ],
      "path" : "/{id}/_history/{vid}/$meta",
      "resourceId" : "6b686c69-b331-491b-98f1-a63e99d1755e",
      "resourceName" : "/{id}/_history/{vid}/$meta",
      "resources" : [ ],
      "revisionNumber" : 1
    } ],
    "customAttributes" : {
      "SWAGGER_RESOURCE_PATH" : "/{id}/_history/{vid}/$meta",
      "SWAGGER_PRODUCES" : "[ \"application/json+fhir;charset=UTF-8\", \"application/xml+fhir;charset=UTF-8\" ]",
      "SWAGGER_PROTOCOLS" : "[ \"https\" ]"
    },
    "createdTime" : 1443788735786,
    "apiRevisionId" : "6a6b9eda-be1d-4215-9d34-087e80c276ac",
    "resources" : [ ],
    "revisionNumber" : 1
  }, {
    "id" : "9a1efecc-5f58-4a83-8c14-c0b43b9359fd",
    "name" : "/{id}/{type}",
    "baseUrl" : "https://fhirsandbox-test.apigee.net/v2/MedicationDispense",
    "path" : "/{id}/{type}",
    "parameters" : [ {
      "dataType" : "string",
      "name" : "Content-Type",
      "options" : [ "application/json+fhir;charset=UTF-8", "application/xml+fhir;charset=UTF-8" ],
      "type" : "header"
    } ],
    "methods" : [ {
      "id" : "4f47baa6-c0c9-41ec-b5f3-c8e85a17e80f",
      "name" : "/{id}/{type}-get",
      "displayName" : "Compartment Search",
      "description" : "<p>Search the specified resource type in MedicationDispense compartment.</p>\n",
      "verb" : "GET",
      "security" : [ "oauth-2-0" ],
      "parameters" : [ {
        "allowMultiple" : false,
        "dataType" : "string",
        "description" : "",
        "name" : "Content-Type",
        "options" : [ "application/json+fhir;charset=UTF-8", "application/xml+fhir;charset=UTF-8" ],
        "required" : false,
        "type" : "header"
      }, {
        "allowMultiple" : false,
        "dataType" : "string",
        "description" : "Format of data to be returned.",
        "name" : "_format",
        "required" : false,
        "type" : "query"
      }, {
        "allowMultiple" : false,
        "dataType" : "string",
        "description" : "The logical resource id associated with the MedicationDispense. Sample ids are: 3426, 3425, 3418, 3423, 5029.",
        "name" : "id",
        "required" : true,
        "type" : "template"
      }, {
        "allowMultiple" : false,
        "dataType" : "string",
        "description" : "Type of Resource",
        "name" : "type",
        "required" : true,
        "type" : "template"
      }, {
        "allowMultiple" : false,
        "dataType" : "string",
        "description" : "Specify access token for API in the following format: Bearer [access_token].",
        "name" : "Authorization",
        "required" : false,
        "type" : "header"
      }, {
        "allowMultiple" : false,
        "dataType" : "string",
        "description" : "The Accept request-header field can be used to specify certain media types which are acceptable for the response.",
        "name" : "Accept",
        "required" : false,
        "type" : "header"
      }, {
        "allowMultiple" : false,
        "dataType" : "string",
        "description" : "The logical resource id associated with the MedicationDispense. Sample ids are: 3426, 3425, 3418, 3423, 5029.",
        "name" : "_id",
        "required" : false,
        "type" : "query"
      }, {
        "allowMultiple" : false,
        "dataType" : "string",
        "description" : "Used to specify set of elements be returned as part of a resource. The _elements parameter consists of a comma separated list of base element names.",
        "name" : "_elements",
        "required" : false,
        "type" : "query"
      }, {
        "allowMultiple" : false,
        "dataType" : "string",
        "description" : "The search parameter _lastUpdated can be used to select resources based on the last time they were changed. The parameter format is yyyy-mm-ddThh:nn:ss(TZ). The prefixes >, >=, <= and < may be used on the parameter value.",
        "name" : "_lastUpdated",
        "required" : false,
        "type" : "query"
      }, {
        "allowMultiple" : false,
        "dataType" : "string",
        "description" : "The search parameter _lastUpdated can be used to select resources based on the last time they were changed. The parameter format is yyyy-mm-ddThh:nn:ss(TZ). The prefixes >, >=, <= and < may be used on the parameter value.",
        "name" : "_lastUpdated",
        "required" : false,
        "type" : "query"
      }, {
        "allowMultiple" : false,
        "dataType" : "string",
        "description" : "This parameter searches on the profile element in the meta element of the resource. Value can have following formats: [code] or [namespace]|[code] or |[code].",
        "name" : "_profile",
        "required" : false,
        "type" : "query"
      }, {
        "allowMultiple" : false,
        "dataType" : "string",
        "description" : "This parameter searches on the tags element in the meta element of the resource. Value can have following formats: [code] or [namespace]|[code] or |[code].",
        "name" : "_tag",
        "required" : false,
        "type" : "query"
      }, {
        "allowMultiple" : false,
        "dataType" : "string",
        "description" : "This parameter searches on the security element in the meta element of the resource. Value can have following formats: [code] or [namespace]|[code] or |[code].",
        "name" : "_security",
        "required" : false,
        "type" : "query"
      }, {
        "allowMultiple" : false,
        "dataType" : "integer",
        "description" : "The number of resources that should be returned in a single page.",
        "name" : "_count",
        "required" : false,
        "type" : "query"
      }, {
        "allowMultiple" : false,
        "dataType" : "boolean",
        "description" : "The _summary parameter requests the server to return only the elements marked as summary in their definition. ",
        "name" : "_summary",
        "required" : false,
        "type" : "query"
      }, {
        "allowMultiple" : false,
        "dataType" : "string",
        "description" : "This parameter can be used to fetch a particular resource, and any resources that it references. Parameter values for _include have 3 parts, separated by a : separator. 1. The name of the source resource from which the join comes. 2. The name of the search parameter which must be of type reference. 3.(Optional) A specific of type of target resource (for when the search parameter refers to multiple possible target types)",
        "name" : "_include",
        "required" : false,
        "type" : "query"
      }, {
        "allowMultiple" : false,
        "dataType" : "string",
        "description" : "This parameter can be used to fetch a particular resource, and any resources that refer to it. It can have a value of one of the possible search parameters. Parameter values for _revinclude have 3 parts, separated by a : separator. 1. The name of the source resource from which the join comes. 2. The name of the search parameter which must be of type reference. 3.(Optional) A specific of type of target resource (for when the search parameter refers to multiple possible target types)",
        "name" : "_revinclude",
        "required" : false,
        "type" : "query"
      }, {
        "allowMultiple" : false,
        "dataType" : "string",
        "description" : "Used to order the results in default(ascending) order. The value can be one of the possible search parameters. The _sort parameter can repeat to indicate sort order, with the repeats indicating a lower sort priority sequentially.",
        "name" : "_sort",
        "required" : false,
        "type" : "query"
      }, {
        "allowMultiple" : false,
        "dataType" : "string",
        "description" : "Used to order the results in ascending order. The value can be one of the possible search parameters. The _sort parameter can repeat to indicate sort order, with the repeats indicating a lower sort priority sequentially.",
        "name" : "_sort:asc",
        "required" : false,
        "type" : "query"
      }, {
        "allowMultiple" : false,
        "dataType" : "string",
        "description" : "Used to order the results in descending order. The value can be one of the possible search parameters. The _sort parameter can repeat to indicate sort order, with the repeats indicating a lower sort priority sequentially.",
        "name" : "_sort:desc",
        "required" : false,
        "type" : "query"
      }, {
        "allowMultiple" : false,
        "dataType" : "string",
        "description" : "Returns dispenses of this medicine code. Value can have following formats: [code] or [system]|[code] or |[code].",
        "name" : "code",
        "required" : false,
        "type" : "query"
      }, {
        "allowMultiple" : false,
        "dataType" : "string",
        "description" : "Return dispenses that should be sent to a specific destination (Location).",
        "name" : "destination",
        "required" : false,
        "type" : "query"
      }, {
        "allowMultiple" : false,
        "dataType" : "string",
        "description" : "Return all dispenses performed by a specific individual (Practitioner).",
        "name" : "dispenser",
        "required" : false,
        "type" : "query"
      }, {
        "allowMultiple" : false,
        "dataType" : "string",
        "description" : "Return dispenses with this external identity. Value can have following formats: [code] or [system]|[code] or |[code].",
        "name" : "identifier",
        "required" : false,
        "type" : "query"
      }, {
        "allowMultiple" : false,
        "dataType" : "string",
        "description" : "Returns dispenses of this medicine (Medication).",
        "name" : "medication",
        "required" : false,
        "type" : "query"
      }, {
        "allowMultiple" : false,
        "dataType" : "string",
        "description" : "The identity of a patient to list dispenses for (Patient).",
        "name" : "patient",
        "required" : false,
        "type" : "query"
      }, {
        "allowMultiple" : false,
        "dataType" : "string",
        "description" : "The identity of a prescription to list dispenses from (MedicationPrescription).",
        "name" : "prescription",
        "required" : false,
        "type" : "query"
      }, {
        "allowMultiple" : false,
        "dataType" : "string",
        "description" : "Who collected the medication (Patient, Practitioner).",
        "name" : "receiver",
        "required" : false,
        "type" : "query"
      }, {
        "allowMultiple" : false,
        "dataType" : "string",
        "description" : "Return all dispenses with the specified responsible party (Practitioner).",
        "name" : "responsibleparty",
        "required" : false,
        "type" : "query"
      }, {
        "allowMultiple" : false,
        "dataType" : "string",
        "description" : "Status of the dispense. Value can have following formats: [code] or [system]|[code] or |[code].",
        "name" : "status",
        "required" : false,
        "type" : "query"
      }, {
        "allowMultiple" : false,
        "dataType" : "string",
        "description" : "Return all dispenses of a specific type. Value can have following formats: [code] or [system]|[code] or |[code].",
        "name" : "type",
        "required" : false,
        "type" : "query"
      }, {
        "allowMultiple" : false,
        "dataType" : "string",
        "description" : "Date when medication handed over to patient (outpatient setting), or supplied to ward or clinic (inpatient setting). The date parameter format is yyyy-mm-ddThh:nn:ss(TZ). The prefixes >, >=, <= and < may be used on the parameter value.",
        "name" : "whenhandedover",
        "required" : false,
        "type" : "query"
      }, {
        "allowMultiple" : false,
        "dataType" : "string",
        "description" : "Date when medication handed over to patient (outpatient setting), or supplied to ward or clinic (inpatient setting). The date parameter format is yyyy-mm-ddThh:nn:ss(TZ). Two dates can be used to specify an interval. The prefixes >, >=, <= and < may be used on the parameter value.",
        "name" : "whenhandedover",
        "required" : false,
        "type" : "query"
      }, {
        "allowMultiple" : false,
        "dataType" : "string",
        "description" : "Date when medication prepared. The date parameter format is yyyy-mm-ddThh:nn:ss(TZ). The prefixes >, >=, <= and < may be used on the parameter value.",
        "name" : "whenprepared",
        "required" : false,
        "type" : "query"
      }, {
        "allowMultiple" : false,
        "dataType" : "string",
        "description" : "Date when medication prepared. The date parameter format is yyyy-mm-ddThh:nn:ss(TZ). Two dates can be used to specify an interval. The prefixes >, >=, <= and < may be used on the parameter value.",
        "name" : "whenprepared",
        "required" : false,
        "type" : "query"
      } ],
      "body" : {
        "attachments" : [ ],
        "contentType" : "application/json+fhir;charset=UTF-8,application/xml+fhir;charset=UTF-8",
        "parameters" : [ ]
      },
      "response" : {
        "errors" : [ ],
        "parameters" : [ ]
      },
      "customAttributes" : {
        "SWAGGER_PRODUCES" : "[ \"application/json+fhir;charset=UTF-8\", \"application/xml+fhir;charset=UTF-8\" ]"
      },
      "createdTime" : 1443788735791,
      "modifiedTime" : 1443796133079,
      "apiRevisionId" : "6a6b9eda-be1d-4215-9d34-087e80c276ac",
      "baseUrl" : "https://fhirsandbox-test.apigee.net/v2/MedicationDispense",
      "methods" : [ ],
      "path" : "/{id}/{type}",
      "resourceId" : "9a1efecc-5f58-4a83-8c14-c0b43b9359fd",
      "resourceName" : "/{id}/{type}",
      "resources" : [ ],
      "revisionNumber" : 1
    } ],
    "customAttributes" : {
      "SWAGGER_RESOURCE_PATH" : "/{id}/{type}",
      "SWAGGER_PRODUCES" : "[ \"application/json+fhir;charset=UTF-8\", \"application/xml+fhir;charset=UTF-8\" ]",
      "SWAGGER_PROTOCOLS" : "[ \"https\" ]"
    },
    "createdTime" : 1443788735786,
    "apiRevisionId" : "6a6b9eda-be1d-4215-9d34-087e80c276ac",
    "resources" : [ ],
    "revisionNumber" : 1
  } ],
  "customAttributes" : {
    "SWAGGER_INFO" : "{\n  \"description\" : \"FHIR MedicationDispense resource API documentation\",\n  \"version\" : \"1.0.0\",\n  \"title\" : \"MedicationDispense API\"\n}",
    "SWAGGER_VERSION" : "2.0"
  },
  "createdTime" : 1443788735755
}